sign_extension.v
/*
The Sign Extension Unit ensures the correct interpretation and manipulation of immediate 
values during instruction execution. In RISC-V, instructions can vary in format (such as 
R-Type, I-Type, S-Type, etc.), and each format has specific fields that need to be extracted 
and processed. The Sign Extension Unit plays a crucial role in reshuffling bits and extending 
immediate values based on the opcode type.
When an instruction is fetched, the Sign Extension Unit determines the instruction's format 
and extracts the necessary value from the relevant fields to compute the new immediate value.
*/

`define INST_WIDTH 32

// RISC-V Base Instruction Set Opcodes
`define OPCODE 7
`define OP_LUI     7'b0110111 // Load Upper Immediate - U-Type
`define OP_AUIPC   7'b0010111 // Add Upper Immediate to PC - U-Type
`define OP_JAL     7'b1101111 // Jump and Link - J-Type 
`define OP_BRANCH  7'b1100011 // Branch Instructions (BEQ, BNE, BLT, etc.)- B-Type
`define OP_STORE   7'b0100011 // Store Instructions (SB, SH, SW) - S-Type
`define OP_ALU     7'b0110011 // ALU Instructions (ADD, SUB, AND, OR, XOR, etc.) - R-Type
`define OP_JALR    7'b1100111 // Jump and Link Register - I-Type
`define OP_LOAD    7'b0000011 // Load Instructions (LB, LH, LW, LBU, LHU) - I-Type
`define OP_ALUI    7'b0010011 // ALU Immediate Instructions (ADDI, ANDI, ORI, XORI, etc.) - I-Type

module sign_extension (
    input wire [`INST_WIDTH-1:0]    i_inst,       
    input wire [`OPCODE-1:0]        i_opcode,
    output reg [`INST_WIDTH-1:0]    o_immediate_extended
);

// Decision making block
always @(*) begin
    case (i_opcode)
        // U-Type Instruction Immediate
        `OP_LUI, `OP_AUIPC    : o_immediate_extended = $signed({i_inst[`INST_WIDTH-1:12], {12{1'b0}}}); 
        
        // UJ-Type Instruction Immediate
        `OP_JAL    : o_immediate_extended = $signed({i_inst[`INST_WIDTH-1], i_inst[19:12], i_inst[20], i_inst[30:21], {12{1'b0}}}) >>> 11; 
        
        // SB-Type Instruction Immediate
        `OP_BRANCH : o_immediate_extended = $signed({i_inst[`INST_WIDTH-1], i_inst[7], i_inst[30:25], i_inst[11:8], {20{1'b0}}}) >>> 19; 
        
        // S-Type Instruction Immediate
        `OP_STORE  : o_immediate_extended = $signed({i_inst[`INST_WIDTH-1:25], i_inst[11:7], {20{1'b0}}}) >>> 20; 
        
        // R-Type Instruction Immediate
        // `OP_ALU    : o_immediate_extended = ; 
        
        // I-Type Instruction Immediate
        `OP_JALR, `OP_LOAD, `OP_ALUI : o_immediate_extended = $signed({i_inst[`INST_WIDTH-1:20], {20{1'b0}}}) >>> 20; 
        default: o_immediate_extended = {`INST_WIDTH{1'b1}};
    endcase
end

endmodule

testbenches/sign_extension/sign_extension_tb.v
`default_nettype none
`timescale 1ns/1ns

`define assert(signal, value) \
        if (signal !== value) begin \
            $display("ASSERTION FAILED at %2d in %m: signal != value", $time); \
            $finish; \
        end

module sign_extension_tb;

  reg clk;
  reg [`INST_WIDTH-1:0] inst = 32'h00000000;
  reg [`OPCODE-1:0] opcode = `OP_ALUI;
  wire [`INST_WIDTH-1:0] immediate_extended;

  sign_extension dut (
    .i_inst(inst),
    .i_opcode(opcode),    
    .o_immediate_extended(immediate_extended)
  );

  initial begin
    clk = 1'b0;
  end

  always #5 clk = ~clk;
  
  initial begin
      inst = 32'h80000000;
      opcode = `OP_ALUI;
    #10;
      `assert(dut.o_immediate_extended, 32'hfffff800);
      inst = 32'h10100000;
      opcode = `OP_LOAD;
    #10;
      `assert(dut.o_immediate_extended, 32'h00000101);
      inst = 32'h80F80023;
      opcode = `OP_STORE;
    #10;
      `assert(dut.o_immediate_extended, 32'hfffff800);
      inst = 32'h00F80023;
      opcode = `OP_STORE;
    #10;
      `assert(dut.o_immediate_extended, 32'h00000000);
      inst = 32'h000170b7;
      opcode = `OP_LUI;
    #10;
      `assert(dut.o_immediate_extended, 32'h00017000);
      inst = 32'h000170b7;
      opcode = `OP_AUIPC;
    #10;        
      `assert(dut.o_immediate_extended, 32'h00017000);
      inst = 32'h0e80026f;
      opcode = `OP_JAL;
    #10;
      `assert(dut.o_immediate_extended, 32'h000000e8);
      inst = 32'hf19ff26f;
      opcode = `OP_JAL;
    #10;
      `assert(dut.o_immediate_extended, 32'hffffff18);
      inst = 32'h00c00167;
      opcode = `OP_JALR;
    #10;
      `assert(dut.o_immediate_extended, 32'h0000000c);
      inst = 32'hfe4104e3;
      opcode = `OP_BRANCH;
    #10;
      `assert(dut.o_immediate_extended, 32'hffffffe8);
    $finish;

  end

  always @(posedge clk) begin 
    $display("time %2t, inst = %8h, opcode = %7b, inst = %8h", $time, inst, opcode, immediate_extended);
  end 
  
  initial begin
    $dumpfile("sign_extension_tb.vcd");
    $dumpvars(0, sign_extension_tb);  
  end

endmodule

testbenches/sign_extension/sign_extension_tb.vcd
$date
	Fri Oct 10 03:09:14 2025
$end
$version
	Icarus Verilog
$end
$timescale
	1ns
$end
$scope module sign_extension_tb $end
$var wire 32 ! immediate_extended [31:0] $end
$var reg 1 " clk $end
$var reg 32 # inst [31:0] $end
$var reg 7 $ opcode [6:0] $end
$scope module dut $end
$var wire 32 % i_inst [31:0] $end
$var wire 7 & i_opcode [6:0] $end
$var reg 32 ' o_immediate_extended [31:0] $end
$upscope $end
$upscope $end
$enddefinitions $end
$comment Show the parameter values. $end
$dumpall
$end
#0
$dumpvars
b11111111111111111111100000000000 '
b10011 &
b10000000000000000000000000000000 %
b10011 $
b10000000000000000000000000000000 #
0"
b11111111111111111111100000000000 !
$end
#5
1"
#10
b100000001 !
b100000001 '
0"
b11 $
b11 &
b10000000100000000000000000000 #
b10000000100000000000000000000 %
#15
1"
#20
b11111111111111111111100000000000 !
b11111111111111111111100000000000 '
0"
b100011 $
b100011 &
b10000000111110000000000000100011 #
b10000000111110000000000000100011 %
#25
1"
#30
b0 !
b0 '
0"
b111110000000000000100011 #
b111110000000000000100011 %
#35
1"
#40
b10111000000000000 !
b10111000000000000 '
0"
b110111 $
b110111 &
b10111000010110111 #
b10111000010110111 %
#45
1"
#50
0"
b10111 $
b10111 &
#55
1"
#60
b11101000 !
b11101000 '
0"
b1101111 $
b1101111 &
b1110100000000000001001101111 #
b1110100000000000001001101111 %
#65
1"
#70
b11111111111111111111111100011000 !
b11111111111111111111111100011000 '
0"
b11110001100111111111001001101111 #
b11110001100111111111001001101111 %
#75
1"
#80
b1100 !
b1100 '
0"
b1100111 $
b1100111 &
b110000000000000101100111 #
b110000000000000101100111 %
#85
1"
#90
b11111111111111111111111111101000 !
b11111111111111111111111111101000 '
0"
b1100011 $
b1100011 &
b11111110010000010000010011100011 #
b11111110010000010000010011100011 %
