branch_unit.v
/*
The branch unit is a critical component in a computer system that facilitates 
decision-making during program execution by determining the flow of control 
based on specific conditions. This unit processes various branch operations, 
allowing the processor to alter its execution path based on the results of 
comparisons. Typically, a program executes instructions in a sequential 
order, one after the other.
*/

`define DATA_WIDTH 32

`define BRANCH_BEQ      3'b000 // Branch Equal
`define BRANCH_BNE      3'b001 // Branch Not Equal
`define BRANCH_BLT      3'b100 // Branch Less Than
`define BRANCH_BGE      3'b101 // Branch Greater Than Or Equal
`define BRANCH_BLTU     3'b110 // Branch Less Than Unsigned
`define BRANCH_BGEU     3'b111 // Branch Greater Than Or Equal Unsigned
`define BRANCH_JAL_JALR 3'b010 // Jump in case of JAL or JALR instrucion

module branch_unit (
    // INPUT
    input wire i_branch,
    input wire [2:0] i_branch_op,
    input wire [`DATA_WIDTH-1:0] i_a,
    input wire [`DATA_WIDTH-1:0] i_b,
    // OUTPUT
    output reg o_take
);

// Mux to decide branching
always @(*) begin
    o_take = 1'b0;
    case (i_branch_op)
        `BRANCH_BEQ      : o_take = (i_branch) ? (i_a == i_b) : 1'b0;
        `BRANCH_BNE      : o_take = (i_branch) ? (i_a != i_b) : 1'b0;
        `BRANCH_BLT      : o_take = (i_branch) ? ($signed(i_a) < $signed(i_b)) : 1'b0;
        `BRANCH_BGE      : o_take = (i_branch) ? ($signed(i_a) >= $signed(i_b)) : 1'b0;
        `BRANCH_BLTU     : o_take = (i_branch) ? (i_a < i_b) : 1'b0;
        `BRANCH_BGEU     : o_take = (i_branch) ? (i_a >= i_b) : 1'b0;
        `BRANCH_JAL_JALR : o_take = i_branch;
        default: o_take = 1'b0;
    endcase
end

endmodule

testbenches/branch_unit/branch_unit_tb.v
`default_nettype none
`timescale 1ns/1ns

`define assert(signal, value) \
        if (signal !== value) begin \
            $display("ASSERTION FAILED at %2d in %m: signal != value", $time); \
            $finish; \
        end

module  branch_unit_tb;

  reg clk;
  reg i_branch = 1'b0;
  reg [2:0] i_branch_op = 3'b000;
  reg [`DATA_WIDTH-1:0] i_a = 32'h00000000;
  reg [`DATA_WIDTH-1:0] i_b = 32'h00000000;
  
  wire o_take;

  branch_unit dut (
    .i_branch(i_branch),
    .i_branch_op(i_branch_op),
    .i_a(i_a),
    .i_b(i_b),
    .o_take(o_take)
  );
  
  initial begin
    clk = 1'b0;
  end

  always #5 clk = ~clk;

  initial begin
      i_a = 32'h00000000;
      i_b = 32'h00000000;
      i_branch = 1'b1;
      i_branch_op = `BRANCH_BEQ;
    #10;
      `assert(dut.o_take, 1'b1);
      i_branch = 1'b1;
      i_branch_op = `BRANCH_BNE;
    #10;
      `assert(dut.o_take, 1'b0);
      i_branch = 1'b1;
      i_branch_op = `BRANCH_BNE;
      i_a = 32'h00000000;
      i_b = 32'h00000001;
    #10;
      `assert(dut.o_take, 1'b1);
      //-1
      i_a = 32'h11111111;
      //-2
      i_b = 32'h11111110;
      i_branch = 1'b1;
      i_branch_op = `BRANCH_BLT;
    #10;
      `assert(dut.o_take, 1'b0);
      i_branch = 1'b1;
      i_branch_op = `BRANCH_BGE;  
    #10;
      `assert(dut.o_take, 1'b1);
      i_branch = 1'b1;
      i_branch_op = `BRANCH_BLTU;  
    #10;
      `assert(dut.o_take, 1'b0);
      i_branch = 1'b1;
      i_branch_op = `BRANCH_BGEU; 
    #10;
      `assert(dut.o_take, 1'b1);
      i_branch = 1'b1;
      i_branch_op = `BRANCH_JAL_JALR;  
    #10;
      `assert(dut.o_take, 1'b1);
      i_branch = 1'b0;
      i_branch_op = `BRANCH_JAL_JALR;  
    #10;
      `assert(dut.o_take, 1'b0);
    $finish;

  end

  always @(posedge clk) begin 
  	$display("time %2t, i_branch = %b, i_branch_op = %3b, i_a = %8h, i_b = %8h, o_take = %b", $time, i_branch, i_branch_op, i_a, i_b, o_take);
  end 
  
  initial begin
    $dumpfile("branch_unit_tb.vcd");
    $dumpvars(0, branch_unit_tb);  
  end

endmodule

testbenches/branch_unit/branch_unit_tb.vcd
$date
	Fri Oct 10 02:53:15 2025
$end
$version
	Icarus Verilog
$end
$timescale
	1ns
$end
$scope module branch_unit_tb $end
$var wire 1 ! o_take $end
$var reg 1 " clk $end
$var reg 32 # i_a [31:0] $end
$var reg 32 $ i_b [31:0] $end
$var reg 1 % i_branch $end
$var reg 3 & i_branch_op [2:0] $end
$scope module dut $end
$var wire 32 ' i_a [31:0] $end
$var wire 32 ( i_b [31:0] $end
$var wire 1 % i_branch $end
$var wire 3 ) i_branch_op [2:0] $end
$var reg 1 ! o_take $end
$upscope $end
$upscope $end
$enddefinitions $end
$comment Show the parameter values. $end
$dumpall
$end
#0
$dumpvars
b0 )
b0 (
b0 '
b0 &
1%
b0 $
b0 #
0"
1!
$end
#5
1"
#10
0!
0"
b1 &
b1 )
#15
1"
#20
1!
0"
b1 $
b1 (
#25
1"
#30
0!
0"
b100 &
b100 )
b10001000100010001000100010000 $
b10001000100010001000100010000 (
b10001000100010001000100010001 #
b10001000100010001000100010001 '
#35
1"
#40
1!
0"
b101 &
b101 )
#45
1"
#50
0!
0"
b110 &
b110 )
#55
1"
#60
1!
0"
b111 &
b111 )
#65
1"
#70
1!
0"
b10 &
b10 )
#75
1"
#80
0!
0"
0%
