alu.v
/*
The ALU (Arithmetic Logic Unit) is a fundamental component of a computer 
system that performs essential arithmetic and logical operations, enabling 
the processor to execute calculations and make decisions based on data. 
It handles a variety of operations, including addition, subtraction, 
bitwise operations, and comparisons, allowing the CPU to process instructions efficiently.
*/

`define DATA_WIDTH 32

// RISC-V ALU Operations
`define OP_ALU_ADD    6'b011001 // Add
`define OP_ALU_SUB    6'b011011 // Subtract
`define OP_ALU_AND    6'b011101 // Bitwise AND
`define OP_ALU_OR     6'b011111 // Bitwise OR
`define OP_ALU_XOR    6'b100001 // Bitwise XOR
`define OP_ALU_SLT    6'b100011 // Set Less Than (signed)
`define OP_ALU_SLTU   6'b100101 // Set Less Than (unsigned)
`define OP_ALU_SLL    6'b100111 // Shift Left Logical
`define OP_ALU_SRL    6'b101001 // Shift Right Logical
`define OP_ALU_SRA    6'b101011 // Shift Right Arithmetic

module alu (
    // INPUT
    input wire [5:0] i_alu_op,
    input wire [`DATA_WIDTH-1:0] i_a,
    input wire [`DATA_WIDTH-1:0] i_b,
    // OUTPUT
    output reg [`DATA_WIDTH-1:0] o_c
);

// ALU unit
always @(*) begin
    case (i_alu_op)
        `OP_ALU_ADD  : o_c = i_a + i_b;
        `OP_ALU_SUB  : o_c = i_a - i_b;
        `OP_ALU_AND  : o_c = i_a & i_b;
        `OP_ALU_OR   : o_c = i_a | i_b;
        `OP_ALU_XOR  : o_c = i_a ^ i_b;
        `OP_ALU_SLT  : o_c = (i_a < i_b) ? 32'd1 : 32'd0;
        `OP_ALU_SLTU : o_c = ($signed(i_a) < $signed(i_b)) ? 32'd1 : 32'd0;
        `OP_ALU_SLL  : o_c = i_a << i_b[4:0];
        `OP_ALU_SRL  : o_c = i_a >> i_b[4:0];
        `OP_ALU_SRA  : o_c = $signed(i_a) >>> i_b[4:0];     // m >>> n : shift m right n-times; fill with value of sign bit if expression is signed, otherwise fill with 0 (Verilog-2001)
        default: o_c = {`DATA_WIDTH{1'b0}};
    endcase
    
end

endmodule

testbenches/alu/alu_tb.v
`default_nettype none
`timescale 1ns/1ns

`define assert(signal, value) \
        if (signal !== value) begin \
            $display("ASSERTION FAILED at %2d in %m: signal != value", $time); \
            $finish; \
        end

module  alu_tb;

  reg clk;
  reg [5:0] i_alu_op = 5'b00000;
  reg [`DATA_WIDTH-1:0] i_a = 32'h00000000;
  reg [`DATA_WIDTH-1:0] i_b = 32'h00000000;
  
  wire [`DATA_WIDTH-1:0] o_c;

  alu dut (
    .i_alu_op(i_alu_op),
    .i_a(i_a),
    .i_b(i_b),
    .o_c(o_c)
  );
  
  initial begin
    clk = 1'b0;
  end

  always #5 clk = ~clk;

  initial begin
        i_a = 32'h00000001;
        i_b = 32'h00000001;
        i_alu_op = `OP_ALU_ADD;
      #10;
        `assert(dut.o_c, 32'h00000002);
        i_a = 32'h00000001;
        i_b = 32'h00000001;
        i_alu_op = `OP_ALU_SUB;
      #10;
        `assert(dut.o_c, 32'h00000000);
        i_a = 32'h00000101;
        i_b = 32'h00010001;
        i_alu_op = `OP_ALU_AND;
      #10;
        `assert(dut.o_c, 32'h00000001);
        i_a = 32'h00000101;
        i_b = 32'h00010001;
        i_alu_op = `OP_ALU_OR;
      #10;
        `assert(dut.o_c, 32'h00010101);
        i_a = 32'h00000101;
        i_b = 32'h00010001;
        i_alu_op = `OP_ALU_XOR;
      #10;
        `assert(dut.o_c, 32'h00010100);
        i_a = 32'h00000101;
        i_b = 32'h00010001;
        i_alu_op = `OP_ALU_SLT;
      #10;
        `assert(dut.o_c, 32'h00000001);
        i_a = 32'h00000001;
        i_b = 32'h00000010;
        i_alu_op = `OP_ALU_SLL;
      #10;
        `assert(dut.o_c, 32'h00010000);
        i_a = 32'h00000100;
        i_b = 32'h00000001;
        i_alu_op = `OP_ALU_SRL;
      #10;
        `assert(dut.o_c, 32'h00000080);
        i_a = 32'hfffffff0;
        i_b = 32'h00000003;
        i_alu_op = `OP_ALU_SRA;
      #10;
        `assert(dut.o_c, 32'hfffffffe);
         i_a = 32'h80000000;
         i_b = 32'h0000001f;
         i_alu_op = `OP_ALU_SRA;
       #10;
        `assert(dut.o_c, 32'hffffffff);
   
    $finish;

  end

  always @(posedge clk) begin 
    $display("time %2t, i_alu_op = %5b, i_a = %8h, i_b = %8h, o_c = %8h", $time, i_alu_op, i_a, i_b, o_c);
  end 
  
  initial begin
    $dumpfile("alu_tb.vcd");
    $dumpvars(0, alu_tb);  
  end

endmodule

testbenches/alu/alu_tb.vcd
$date
	Fri Oct 10 02:40:54 2025
$end
$version
	Icarus Verilog
$end
$timescale
	1ns
$end
$scope module alu_tb $end
$var wire 32 ! o_c [31:0] $end
$var reg 1 " clk $end
$var reg 32 # i_a [31:0] $end
$var reg 6 $ i_alu_op [5:0] $end
$var reg 32 % i_b [31:0] $end
$scope module dut $end
$var wire 32 & i_a [31:0] $end
$var wire 6 ' i_alu_op [5:0] $end
$var wire 32 ( i_b [31:0] $end
$var reg 32 ) o_c [31:0] $end
$upscope $end
$upscope $end
$enddefinitions $end
$comment Show the parameter values. $end
$dumpall
$end
#0
$dumpvars
b10 )
b1 (
b11001 '
b1 &
b1 %
b11001 $
b1 #
0"
b10 !
$end
#5
1"
#10
b0 !
b0 )
0"
b11011 $
b11011 '
#15
1"
#20
b1 !
b1 )
0"
b11101 $
b11101 '
b10000000000000001 %
b10000000000000001 (
b100000001 #
b100000001 &
#25
1"
#30
b10000000100000001 !
b10000000100000001 )
0"
b11111 $
b11111 '
#35
1"
#40
b10000000100000000 !
b10000000100000000 )
0"
b100001 $
b100001 '
#45
1"
#50
b1 !
b1 )
0"
b100011 $
b100011 '
#55
1"
#60
b10000000000000000 !
b10000000000000000 )
0"
b100111 $
b100111 '
b10000 %
b10000 (
b1 #
b1 &
#65
1"
#70
b10000000 !
b10000000 )
0"
b101001 $
b101001 '
b1 %
b1 (
b100000000 #
b100000000 &
#75
1"
#80
b11111111111111111111111111111110 !
b11111111111111111111111111111110 )
0"
b101011 $
b101011 '
b11 %
b11 (
b11111111111111111111111111110000 #
b11111111111111111111111111110000 &
#85
1"
#90
b11111111111111111111111111111111 !
b11111111111111111111111111111111 )
0"
b11111 %
b11111 (
b10000000000000000000000000000000 #
b10000000000000000000000000000000 &
